README.md
go_library/__init__.py
go_library/amigo_solr/__init__.py
go_library/amigo_solr/amigo_cli.py
go_library/amigo_solr/engine.py
go_library/datamodel/__init__.py
go_library/datamodel/amigo_solr.py
go_library/datamodel/amigo_solr_api.py
go_library/datamodel/gocam.py
go_library/datamodel/gocam_api.py
go_library/datamodel/gocam_queries.py
go_library/gocam_cli.py
go_library/implementations/__init__.py
go_library/implementations/gocam_store.py
go_library/sqla/gocam.py
go_library/utils/__init__.py
go_library/utils/bulkloaders.py
go_library/utils/sqlite_utils.py
go_library-0.1.0.dist-info/entry_points.txt
go_library-0.1.0.dist-info/LICENSE
go_library-0.1.0.dist-info/WHEEL
go_library-0.1.0.dist-info/METADATA
go_library-0.1.0.dist-info/RECORD
